{"ref":"1617825f-8af5-4ec2-9cdb-136d0a436e7c","content":"{\"version\":2,\"machineId\":\"006fe862-3553-4c00-a4f9-f65be9fca686\",\"content\":\"{\\\"settings\\\":\\\"{\\\\n    \\\\\\\"workbench.iconTheme\\\\\\\": \\\\\\\"material-icon-theme\\\\\\\",\\\\n    \\\\\\\"workbench.colorTheme\\\\\\\": \\\\\\\"Dracula\\\\\\\",\\\\n    \\\\\\\"files.autoSave\\\\\\\": \\\\\\\"afterDelay\\\\\\\",\\\\n    \\\\\\\"editor.fontFamily\\\\\\\": \\\\\\\"'Fira Code'\\\\\\\",\\\\n    \\\\\\\"editor.wordWrap\\\\\\\": \\\\\\\"on\\\\\\\",\\\\n    \\\\\\\"workbench.editor.enablePreview\\\\\\\": false,\\\\n    \\\\\\\"editor.mouseWheelZoom\\\\\\\": true,\\\\n    \\\\\\\"editor.fontLigatures\\\\\\\": true,\\\\n    \\\\\\\"editor.formatOnPaste\\\\\\\": true,\\\\n    \\\\\\\"editor.snippetSuggestions\\\\\\\": \\\\\\\"bottom\\\\\\\",\\\\n    \\\\\\\"html-css-class-completion.enableEmmetSupport\\\\\\\": true,\\\\n    \\\\\\\"vim.cursorStylePerMode.insert\\\\\\\": \\\\\\\"line\\\\\\\",\\\\n    \\\\\\\"vim.cursorStylePerMode.normal\\\\\\\": \\\\\\\"block\\\\\\\",\\\\n    \\\\\\\"vim.insertModeKeyBindings\\\\\\\": [\\\\n    {\\\\n            \\\\\\\"before\\\\\\\": [\\\\\\\"k\\\\\\\", \\\\\\\"j\\\\\\\"],\\\\n            \\\\\\\"after\\\\\\\": [\\\\\\\"<Esc>\\\\\\\"]\\\\n        }\\\\n    ],\\\\n    \\\\\\\"window.zoomLevel\\\\\\\": 0,\\\\n    \\\\\\\"editor.fontSize\\\\\\\": 16,\\\\n    \\\\\\\"editor.minimap.enabled\\\\\\\": false,\\\\n    \\\\\\\"telemetry.enableTelemetry\\\\\\\": false,\\\\n    \\\\\\\"files.insertFinalNewline\\\\\\\": true,\\\\n    \\\\\\\"files.trimTrailingWhitespace\\\\\\\": true,\\\\n    \\\\\\\"window.menuBarVisibility\\\\\\\": \\\\\\\"toggle\\\\\\\",\\\\n    \\\\\\\"editor.cursorSmoothCaretAnimation\\\\\\\": true,\\\\n    \\\\\\\"workbench.list.smoothScrolling\\\\\\\": true\\\\n}\\\"}\"}"}